yffpy/__init__.py
yffpy/data.py
yffpy/models.py
yffpy/query.py
yffpy/utils.py
yffpy-2.11.0.dist-info/LICENSE
yffpy-2.11.0.dist-info/METADATA
yffpy-2.11.0.dist-info/WHEEL
yffpy-2.11.0.dist-info/top_level.txt
yffpy-2.11.0.dist-info/RECORD
