Metadata-Version: 2.1
Name: yffpy
Version: 2.11.0
Summary: DEPRECATED for https://pypi.org/project/yfpy/
Home-page: https://github.com/uberfastman/yffpy
Author: Wren J. R.
Author-email: wrenjr@yahoo.com
License: UNKNOWN
Keywords: yahoo fantasy sports api wrapper nfl football nhl hockey mlb baseball nba basketball
Platform: UNKNOWN
Classifier: Programming Language :: Python :: 3
Classifier: Programming Language :: Python :: 3.7
Classifier: License :: OSI Approved :: GNU General Public License v3 (GPLv3)
Classifier: Operating System :: OS Independent
Classifier: Development Status :: 4 - Beta
Classifier: Topic :: Software Development :: Libraries :: Python Modules
Classifier: Environment :: Console
Classifier: Intended Audience :: Developers
Requires-Python: >=3.5
Requires-Dist: yfpy (==3.0.0)
